README.rst
setup.py
kundalini/__init__.py
kundalini/frame_management.py
kundalini/gl.py
kundalini/matrix.py
kundalini/vector.py
kundalini.egg-info/PKG-INFO
kundalini.egg-info/SOURCES.txt
kundalini.egg-info/dependency_links.txt
kundalini.egg-info/requires.txt
kundalini.egg-info/top_level.txt