Metadata-Version: 1.1
Name: kundalini
Version: 0.4
Summary: LÖVE-like PyGame API
Home-page: https://bitbucket.org/cacilhas/kundalini
Author: Rodrigo Arĥimedeς ℳontegasppa ℭacilhας
Author-email: batalema@cacilhas.info
License: BSD 3-Clausule License
Download-URL: https://bitbucket.org/cacilhas/kundalini/branch/master
Platform: any
Classifier: License :: OSI Approved :: BSD License
Classifier: Operating System :: OS Independent
Classifier: Programming Language :: Python :: 3.4
Classifier: Topic :: Games/Entertainment
Classifier: Topic :: Software Development :: Libraries :: Python Modules
